dnsdb2/__init__.py
dnsdb2/client.py
dnsdb2/exceptions.py
dnsdb2/mock.py
dnsdb2/saf.py
dnsdb2-1.1.5.dist-info/licenses/LICENSE
dnsdb2-1.1.5.dist-info/METADATA
dnsdb2-1.1.5.dist-info/WHEEL
dnsdb2-1.1.5.dist-info/top_level.txt
dnsdb2-1.1.5.dist-info/zip-safe
dnsdb2-1.1.5.dist-info/RECORD
