Metadata-Version: 2.4
Name: dnsdb2
Version: 1.1.5
Summary: Client for DNSDB API version 2 with Flexible Search
Author: Farsight Security, Inc.
Author-email: support@farsightsecurity.com
License: Apache 2.0
Classifier: Development Status :: 5 - Production/Stable
Classifier: License :: OSI Approved :: Apache Software License
Classifier: Programming Language :: Python :: 3
Classifier: Programming Language :: Python :: 3.6
Classifier: Programming Language :: Python :: 3.7
Classifier: Programming Language :: Python :: 3.8
Classifier: Programming Language :: Python :: 3.9
Classifier: Topic :: Internet :: Name Service (DNS)
Classifier: Topic :: Security
Classifier: Topic :: Software Development :: Libraries :: Python Modules
License-File: LICENSE
Requires-Dist: requests
Requires-Dist: importlib; python_version < "3.1"
Requires-Dist: importlib-metadata; python_version < "3.8"
Provides-Extra: test
Requires-Dist: requests-mock; extra == "test"
Dynamic: license-file
